matrixmul_pkg/__init__.py
matrixmul_pkg/matrixmul.py
matrixmul_pkg-0.1.0.dist-info/LICENSE
matrixmul_pkg-0.1.0.dist-info/METADATA
matrixmul_pkg-0.1.0.dist-info/WHEEL
matrixmul_pkg-0.1.0.dist-info/top_level.txt
matrixmul_pkg-0.1.0.dist-info/RECORD
