Metadata-Version: 2.1
Name: matrixmul-pkg
Version: 0.1.0
Summary: An example for teaching how to publish a Python package
Home-page: UNKNOWN
Author: Qing Shen
Author-email: wangqing19890117@163.com
License: UNKNOWN
Platform: UNKNOWN
